odoo/addons/product_pricelist_direct_print_company_group/README.rst
odoo/addons/product_pricelist_direct_print_company_group/__init__.py
odoo/addons/product_pricelist_direct_print_company_group/__manifest__.py
odoo/addons/product_pricelist_direct_print_company_group/i18n/es.po
odoo/addons/product_pricelist_direct_print_company_group/i18n/it.po
odoo/addons/product_pricelist_direct_print_company_group/i18n/product_pricelist_direct_print_company_group.pot
odoo/addons/product_pricelist_direct_print_company_group/readme/CONTRIBUTORS.rst
odoo/addons/product_pricelist_direct_print_company_group/readme/DESCRIPTION.rst
odoo/addons/product_pricelist_direct_print_company_group/readme/USAGE.rst
odoo/addons/product_pricelist_direct_print_company_group/static/description/icon.png
odoo/addons/product_pricelist_direct_print_company_group/static/description/index.html
odoo/addons/product_pricelist_direct_print_company_group/wizards/__init__.py
odoo/addons/product_pricelist_direct_print_company_group/wizards/product_pricelist_print.py
odoo14_addon_product_pricelist_direct_print_company_group-14.0.1.0.1.dev7.dist-info/METADATA
odoo14_addon_product_pricelist_direct_print_company_group-14.0.1.0.1.dev7.dist-info/WHEEL
odoo14_addon_product_pricelist_direct_print_company_group-14.0.1.0.1.dev7.dist-info/top_level.txt
odoo14_addon_product_pricelist_direct_print_company_group-14.0.1.0.1.dev7.dist-info/RECORD
